getindianname/__init__.py
getindianname/femalename.txt
getindianname/femaletitle.txt
getindianname/main.py
getindianname/malename.txt
getindianname/maletitle.txt
getindianname/pyversion.txt
getindianname-1.0.7.dist-info/LICENSE
getindianname-1.0.7.dist-info/METADATA
getindianname-1.0.7.dist-info/WHEEL
getindianname-1.0.7.dist-info/entry_points.txt
getindianname-1.0.7.dist-info/top_level.txt
getindianname-1.0.7.dist-info/RECORD
