Metadata-Version: 2.1
Name: getindianname
Version: 1.0.7
Summary: Generate names based on India. Generate more than 70K unique name within 5 seconds. Names Automaticaly added and updated. About 10+ names were added daily.
Home-page: https://github.com/TechUX/getindianname
Author: Devesh Singh
License: MIT
Platform: UNKNOWN
Classifier: Environment :: Console
Classifier: License :: OSI Approved :: MIT License
Classifier: Operating System :: OS Independent
Classifier: Programming Language :: Python
Classifier: Programming Language :: Python :: 2.7
Classifier: Programming Language :: Python :: 3
License-File: LICENSE
